nomoclip/__init__.py
nomoclip/acgu_colored.npz
nomoclip/attention_graph.py
nomoclip/cli.py
nomoclip/high_attention_region.py
nomoclip/install.sh
nomoclip/instinct_inf.py
nomoclip/model_predict.py
nomoclip/model_train.py
nomoclip/position_inf.py
nomoclip/seq_motifs.py
nomoclip/structure_inf.py
nomoclip/structure_motifs.py
nomoclip/visualization.py
NoMoCLIP-1.0.0.dist-info/LICENSE
NoMoCLIP-1.0.0.dist-info/METADATA
NoMoCLIP-1.0.0.dist-info/WHEEL
NoMoCLIP-1.0.0.dist-info/entry_points.txt
NoMoCLIP-1.0.0.dist-info/top_level.txt
NoMoCLIP-1.0.0.dist-info/RECORD
