Metadata-Version: 2.1
Name: NoMoCLIP
Version: 1.0.0
Summary: Interpretable Modeling of RNA–Protein Interactions from eCLIP-Seq Profiles for Motif-Free RBPs
Author-email: "Yuning Yang, Qiongyao Yu, Xinyuan Zhao and Xiangtao Li" <yangyn533@nenu.edu.cn>
License: MIT License
Keywords: Deep learning,RNA-binding protein,Post-transcriptional regulation
Classifier: Development Status :: 5 - Production/Stable
Classifier: Operating System :: OS Independent
Classifier: License :: OSI Approved :: MIT License
Classifier: Intended Audience :: Developers
Classifier: Intended Audience :: Education
Classifier: Intended Audience :: Science/Research
Classifier: Topic :: Scientific/Engineering :: Artificial Intelligence
Classifier: Programming Language :: Python :: 3
Classifier: Programming Language :: Python :: 3.7
Requires-Python: >=3.7.16
License-File: LICENSE
Requires-Dist: click >=8.0
